google_auth_httplib2.py
google_auth_httplib2-0.0.4.dist-info/LICENSE
google_auth_httplib2-0.0.4.dist-info/METADATA
google_auth_httplib2-0.0.4.dist-info/WHEEL
google_auth_httplib2-0.0.4.dist-info/top_level.txt
google_auth_httplib2-0.0.4.dist-info/RECORD
