Metadata-Version: 1.1
Name: google-auth-httplib2
Version: 0.0.4
Summary: Google Authentication Library: httplib2 transport
Home-page: https://github.com/GoogleCloudPlatform/google-auth-library-python-httplib2
Author: Google Cloud Platform
Author-email: jonwayne+google-auth@google.com
License: Apache 2.0
Keywords: google auth oauth client
Platform: UNKNOWN
Classifier: Programming Language :: Python :: 2
Classifier: Programming Language :: Python :: 2.7
Classifier: Programming Language :: Python :: 3
Classifier: Programming Language :: Python :: 3.4
Classifier: Programming Language :: Python :: 3.5
Classifier: Programming Language :: Python :: 3.6
Classifier: Development Status :: 3 - Alpha
Classifier: Intended Audience :: Developers
Classifier: License :: OSI Approved :: Apache Software License
Classifier: Operating System :: POSIX
Classifier: Operating System :: Microsoft :: Windows
Classifier: Operating System :: MacOS :: MacOS X
Classifier: Operating System :: OS Independent
Classifier: Topic :: Internet :: WWW/HTTP
